{"projects": {"1": {"name": "R Iris", "path": "/Users/david/Dokumente Lokal/UP/Work/Forester/src/forester/instance/data/R Iris", "created": "2022-12-21T09:33:51.719683", "modified": "2022-12-21T09:33:51.719683", "author": "Forester Team", "example": true, "uuid": "78f02c7f-6142-4071-99af-56a3bcedc7a3", "size": 1145, "files": {"tree": "tree.json"}}, "2": {"name": "Matlab Fanny", "path": "/Users/david/Dokumente Lokal/UP/Work/Forester/src/forester/instance/data/Matlab Fanny", "created": "2022-12-21T09:33:51.721473", "modified": "2022-12-21T09:33:51.721473", "author": "Forester Team", "example": true, "uuid": "bc407535-aa4b-4ada-bbf9-f3dfa155369e", "size": 22934, "files": {"tree": "tree.json"}}, "3": {"name": "R Diabetes", "path": "/Users/david/Dokumente Lokal/UP/Work/Forester/src/forester/instance/data/R Diabetes", "created": "2022-12-21T09:33:51.723456", "modified": "2022-12-21T09:33:51.723456", "author": "Forester Team", "example": true, "uuid": "e445d8fb-2ac8-4c88-9219-4ca9f28986a4", "size": 3741, "files": {"tree": "tree.json"}}, "4": {"name": "Matlab Iris", "path": "/Users/david/Dokumente Lokal/UP/Work/Forester/src/forester/instance/data/Matlab Iris", "created": "2022-12-21T09:33:51.725665", "modified": "2022-12-21T09:33:51.725665", "author": "Forester Team", "example": true, "uuid": "db3d99a5-3766-41d8-9ee3-5ac0b730675b", "size": 1211, "files": {"tree": "tree.json"}}}}